{"id":677,"name":"\u00c1o ch\u1ea1y b\u1ed9 n\u1eef m\u00e0u t\u00edm cam form Slimfit","slug":"ao-chay-bo-nu-mau-tim-cam-form-slimfit","permalink":"https:\/\/mayaopickleball.vn\/ao-chay-bo-nu-mau-tim-cam-form-slimfit\/","date_created":"2025-05-31T08:31:24","date_created_gmt":"2025-05-31T08:31:24","date_modified":"2025-06-04T16:42:28","date_modified_gmt":"2025-06-04T16:42:28","type":"simple","status":"publish","featured":false,"catalog_visibility":"visible","description":"<blockquote><p><strong>Ph\u00e1 c\u00e1ch v\u1edbi thi\u1ebft k\u1ebf gradient t\u00edm \u2013 cam r\u1ef1c r\u1ee1, \u00e1o ch\u1ea1y b\u1ed9 n\u1eef form Slimfit l\u00e0 s\u1ef1 l\u1ef1a ch\u1ecdn ho\u00e0n h\u1ea3o cho nh\u1eefng ai y\u00eau th\u00edch phong c\u00e1ch th\u1ec3 thao th\u1eddi th\u01b0\u1ee3ng, n\u0103ng \u0111\u1ed9ng v\u00e0 linh ho\u1ea1t v\u1eadn \u0111\u1ed9ng.<\/strong><\/p><\/blockquote>\n<figure style=\"text-align:center\">\n  <img src=\"https:\/\/cdn.mayaochaybo.vn\/wp-content\/uploads\/2025\/05\/ao-chay-bo-nu-form-slimfit.jpg\" alt=\"\u00c1o ch\u1ea1y b\u1ed9 n\u1eef m\u00e0u t\u00edm cam form Slimfit\" style=\"max-width:100%;height:auto\" \/><figcaption>\u00c1o ch\u1ea1y b\u1ed9 n\u1eef<\/figcaption><\/figure>\n<h2>Thi\u1ebft k\u1ebf th\u1eddi th\u01b0\u1ee3ng, n\u1ed5i b\u1eadt gi\u1eefa \u0111\u00e1m \u0111\u00f4ng<\/h2>\n<p>Chi\u1ebfc \u00e1o ch\u1ea1y b\u1ed9 n\u1eef v\u1edbi <strong>t\u00f4ng m\u00e0u chuy\u1ec3n s\u1eafc Gradient t\u1eeb t\u00edm sang cam<\/strong> kh\u00f4ng ch\u1ec9 mang l\u1ea1i v\u1ebb \u0111\u1eb9p \u1ea5n t\u01b0\u1ee3ng trong t\u1eebng b\u01b0\u1edbc ch\u1ea1y m\u00e0 c\u00f2n th\u1ec3 hi\u1ec7n c\u00e1 t\u00ednh m\u1ea1nh m\u1ebd, hi\u1ec7n \u0111\u1ea1i. Nh\u1eefng h\u1ecda ti\u1ebft h\u00ecnh h\u1ecdc s\u1eafc s\u1ea3o \u0111an xen kh\u00e9o l\u00e9o t\u1ea1o chi\u1ec1u s\u00e2u th\u1ecb gi\u00e1c, ph\u00f9 h\u1ee3p v\u1edbi xu h\u01b0\u1edbng th\u1eddi trang th\u1ec3 thao n\u0103ng \u0111\u1ed9ng hi\u1ec7n nay.<\/p>\n<h2>Tho\u1ea3i m\u00e1i v\u00e0 linh ho\u1ea1t trong t\u1eebng chuy\u1ec3n \u0111\u1ed9ng<\/h2>\n<p>\u0110\u01b0\u1ee3c l\u00e0m t\u1eeb <strong>ch\u1ea5t li\u1ec7u v\u1ea3i co gi\u00e3n cao c\u1ea5p<\/strong>, \u00e1o \u00f4m s\u00e1t body theo form Slimfit nh\u01b0ng v\u1eabn \u0111\u1ea3m b\u1ea3o \u0111\u1ed9 nh\u1eb9 nh\u00e0ng, linh ho\u1ea1t khi v\u1eadn \u0111\u1ed9ng. D\u00f9 b\u1ea1n ch\u1ea1y b\u1ed9 c\u01b0\u1eddng \u0111\u1ed9 cao hay ch\u1ec9 \u0111\u01a1n gi\u1ea3n l\u00e0 \u0111i b\u1ed9 bu\u1ed5i s\u00e1ng, \u00e1o \u0111\u1ea3m b\u1ea3o \u00f4m nh\u1eb9 c\u01a1 th\u1ec3 m\u00e0 kh\u00f4ng g\u00e2y g\u00f2 b\u00f3.<\/p>\n<h2>Tho\u00e1ng kh\u00ed \u2013 Kh\u00f4 nhanh \u2013 Th\u1ea5m h\u00fat m\u1ed3 h\u00f4i<\/h2>\n<p>Kh\u00f4ng ch\u1ec9 \u0111\u1eb9p m\u1eaft, \u00e1o c\u00f2n t\u00edch h\u1ee3p <strong>kh\u1ea3 n\u0103ng th\u1ea5m h\u00fat m\u1ed3 h\u00f4i c\u1ef1c t\u1ed1t<\/strong>, gi\u00fap gi\u1eef cho c\u01a1 th\u1ec3 lu\u00f4n kh\u00f4 r\u00e1o v\u00e0 d\u1ec5 ch\u1ecbu trong su\u1ed1t bu\u1ed5i t\u1eadp. V\u1ea3i c\u00f3 t\u00ednh n\u0103ng <strong>kh\u00f4 nhanh<\/strong>, h\u1ea1n ch\u1ebf m\u00f9i c\u01a1 th\u1ec3 v\u00e0 gi\u00fap b\u1ea1n lu\u00f4n c\u1ea3m th\u1ea5y d\u1ec5 ch\u1ecbu, k\u1ec3 c\u1ea3 sau khi gi\u1eb7t ho\u1eb7c t\u1eadp luy\u1ec7n n\u1eb7ng.<\/p>\n<h2>Nhi\u1ec1u m\u00e0u s\u1eafc, tu\u1ef3 ch\u1ecdn linh ho\u1ea1t<\/h2>\n<p>B\u00ean c\u1ea1nh b\u1ea3n ph\u1ed1i t\u00edm cam n\u1ed5i b\u1eadt, \u00e1o c\u00f2n c\u00f3 c\u00e1c l\u1ef1a ch\u1ecdn m\u00e0u s\u1eafc kh\u00e1c nh\u01b0 xanh, \u0111\u1ecf, t\u00edm, xanh navy \u2013 ph\u00f9 h\u1ee3p cho c\u00e1 nh\u00e2n l\u1eabn nh\u00f3m ch\u1ea1y b\u1ed9, \u0111\u1ed9i th\u1ec3 thao ho\u1eb7c \u0111\u1ed3ng ph\u1ee5c gi\u1ea3i ch\u1ea1y. T\u00f9y t\u1eebng s\u1eafc m\u00e0u m\u00e0 b\u1ea1n c\u00f3 th\u1ec3 mix &amp; match c\u00f9ng ph\u1ee5 ki\u1ec7n th\u1ec3 thao ph\u00f9 h\u1ee3p.<\/p>\n<h3>Th\u00f4ng tin chi ti\u1ebft:<\/h3>\n<ul>\n<li>Form: Slimfit n\u1eef<\/li>\n<li>M\u00e0u ch\u1ee7 \u0111\u1ea1o: Gradient t\u00edm \u2013 cam<\/li>\n<li>Ch\u1ea5t li\u1ec7u: V\u1ea3i co gi\u00e3n, th\u1ea5m h\u00fat m\u1ed3 h\u00f4i, tho\u00e1ng kh\u00ed, kh\u00f4 nhanh<\/li>\n<li>\u0110\u1ed1i t\u01b0\u1ee3ng: N\u1eef s\u1eed d\u1ee5ng trong c\u00e1c ho\u1ea1t \u0111\u1ed9ng th\u1ec3 d\u1ee5c th\u1ec3 thao, ch\u1ea1y b\u1ed9 h\u00e0ng ng\u00e0y<\/li>\n<\/ul>\n<p>H\u00e3y \u0111\u1ec3 m\u1ed7i b\u01b0\u1edbc ch\u1ea1y c\u1ee7a b\u1ea1n tr\u1edf n\u00ean phong c\u00e1ch v\u00e0 tr\u00e0n \u0111\u1ea7y c\u1ea3m h\u1ee9ng v\u1edbi chi\u1ebfc \u00e1o ch\u1ea1y b\u1ed9 chu\u1ea9n form, chu\u1ea9n gu v\u00e0 ho\u00e0n h\u1ea3o v\u1ec1 hi\u1ec7u n\u0103ng!<\/p>\n","short_description":"<p>\u00c1o ch\u1ea1y b\u1ed9 n\u1eef form Slimfit n\u1ed5i b\u1eadt v\u1edbi thi\u1ebft k\u1ebf chuy\u1ec3n m\u00e0u t\u00edm \u2013 cam hi\u1ec7n \u0111\u1ea1i, ch\u1ea5t li\u1ec7u co gi\u00e3n, th\u1ea5m h\u00fat m\u1ed3 h\u00f4i v\u00e0 tho\u00e1ng kh\u00ed, mang l\u1ea1i tr\u1ea3i nghi\u1ec7m tho\u1ea3i m\u00e1i, th\u1eddi trang cho v\u1eadn \u0111\u1ed9ng h\u00e0ng ng\u00e0y.<\/p>\n","sku":"","price":"189000","regular_price":"189000","sale_price":"","date_on_sale_from":null,"date_on_sale_from_gmt":null,"date_on_sale_to":null,"date_on_sale_to_gmt":null,"on_sale":false,"purchasable":false,"total_sales":0,"virtual":false,"downloadable":false,"downloads":[],"download_limit":-1,"download_expiry":-1,"external_url":"","button_text":"","tax_status":"taxable","tax_class":"","manage_stock":false,"stock_quantity":null,"backorders":"no","backorders_allowed":false,"backordered":false,"low_stock_amount":null,"sold_individually":false,"weight":"","dimensions":{"length":"","width":"","height":""},"shipping_required":true,"shipping_taxable":true,"shipping_class":"","shipping_class_id":0,"reviews_allowed":true,"average_rating":"0.00","rating_count":0,"upsell_ids":[],"cross_sell_ids":[],"parent_id":0,"purchase_note":"","categories":[{"id":71,"name":"\u00c1o Ch\u1ea1y B\u1ed9 C\u00f3 Tay","slug":"ao-chay-bo-co-tay"}],"brands":[],"tags":[{"id":80,"name":"\u00e1o ch\u1ea1y b\u1ed9 n\u1eef","slug":"ao-chay-bo-nu"}],"images":[{"id":675,"date_created":"2025-05-31T08:31:07","date_created_gmt":"2025-05-31T08:31:07","date_modified":"2025-05-31T08:31:23","date_modified_gmt":"2025-05-31T08:31:23","src":"https:\/\/cdn.mayaochaybo.vn\/wp-content\/uploads\/2025\/05\/ao-chay-bo-nu-form-slimfit.jpg","name":"ao-chay-bo-nu-form-slimfit","alt":"ao-chay-bo-nu-form-slimfit"},{"id":676,"date_created":"2025-05-31T08:31:24","date_created_gmt":"2025-05-31T08:31:24","date_modified":"2025-05-31T08:31:24","date_modified_gmt":"2025-05-31T08:31:24","src":"https:\/\/cdn.mayaochaybo.vn\/wp-content\/uploads\/2025\/05\/ao-chay-bo-nu-form-slimfit-1.jpg","name":"ao-chay-bo-nu-form-slimfit-1.jpg","alt":"ao-chay-bo-nu-form-slimfit-1.jpg"}],"attributes":[],"default_attributes":[],"variations":[],"grouped_products":[],"menu_order":0,"price_html":"<span class=\"woocommerce-Price-amount amount\"><bdi>189.000&nbsp;<span class=\"woocommerce-Price-currencySymbol\">&#8363;<\/span><\/bdi><\/span>","related_ids":[686,656,632,635,665],"meta_data":[{"id":20240,"key":"_yoast_wpseo_metadesc","value":"\u00c1o ch\u1ea1y b\u1ed9 n\u1eef form Slimfit n\u1ed5i b\u1eadt v\u1edbi thi\u1ebft k\u1ebf chuy\u1ec3n m\u00e0u t\u00edm \u2013 cam hi\u1ec7n \u0111\u1ea1i, ch\u1ea5t li\u1ec7u co gi\u00e3n, th\u1ea5m h\u00fat m\u1ed3 h\u00f4i v\u00e0 tho\u00e1ng kh\u00ed, mang l\u1ea1i tr\u1ea3i nghi\u1ec7m tho\u1ea3i m..."},{"id":22178,"key":"_yoast_wpseo_focuskw","value":"\u00e1o ch\u1ea1y b\u1ed9 n\u1eef m\u00e0u t\u00edm cam"}],"stock_status":"instock","has_options":false,"post_password":"","global_unique_id":"","yoast_head":"<!-- This site is optimized with the Yoast SEO Premium plugin v24.5 (Yoast SEO v25.6) - https:\/\/yoast.com\/wordpress\/plugins\/seo\/ -->\n<title>\u00c1o ch\u1ea1y b\u1ed9 n\u1eef m\u00e0u t\u00edm cam form Slimfit - May \u00c1o Ch\u1ea1y B\u1ed9 - VN<\/title>\n<meta name=\"description\" content=\"\u00c1o ch\u1ea1y b\u1ed9 n\u1eef form Slimfit n\u1ed5i b\u1eadt v\u1edbi thi\u1ebft k\u1ebf chuy\u1ec3n m\u00e0u t\u00edm \u2013 cam hi\u1ec7n \u0111\u1ea1i, ch\u1ea5t li\u1ec7u co gi\u00e3n, th\u1ea5m h\u00fat m\u1ed3 h\u00f4i v\u00e0 tho\u00e1ng kh\u00ed, mang l\u1ea1i tr\u1ea3i nghi\u1ec7m tho\u1ea3i m...\" class=\"yoast-seo-meta-tag\" \/>\n<meta name=\"robots\" content=\"index, follow, max-snippet:-1, max-image-preview:large, max-video-preview:-1\" \/>\n<link rel=\"canonical\" href=\"https:\/\/mayaopickleball.vn\/ao-chay-bo-nu-mau-tim-cam-form-slimfit\/\" class=\"yoast-seo-meta-tag\" \/>\n<meta property=\"og:locale\" content=\"vi_VN\" class=\"yoast-seo-meta-tag\" \/>\n<meta property=\"og:type\" content=\"article\" class=\"yoast-seo-meta-tag\" \/>\n<meta property=\"og:title\" content=\"\u00c1o ch\u1ea1y b\u1ed9 n\u1eef m\u00e0u t\u00edm cam form Slimfit\" class=\"yoast-seo-meta-tag\" \/>\n<meta property=\"og:description\" content=\"\u00c1o ch\u1ea1y b\u1ed9 n\u1eef form Slimfit n\u1ed5i b\u1eadt v\u1edbi thi\u1ebft k\u1ebf chuy\u1ec3n m\u00e0u t\u00edm \u2013 cam hi\u1ec7n \u0111\u1ea1i, ch\u1ea5t li\u1ec7u co gi\u00e3n, th\u1ea5m h\u00fat m\u1ed3 h\u00f4i v\u00e0 tho\u00e1ng kh\u00ed, mang l\u1ea1i tr\u1ea3i nghi\u1ec7m tho\u1ea3i m...\" class=\"yoast-seo-meta-tag\" \/>\n<meta property=\"og:url\" content=\"https:\/\/mayaopickleball.vn\/ao-chay-bo-nu-mau-tim-cam-form-slimfit\/\" class=\"yoast-seo-meta-tag\" \/>\n<meta property=\"og:site_name\" content=\"May \u00c1o Ch\u1ea1y B\u1ed9 - VN\" class=\"yoast-seo-meta-tag\" \/>\n<meta property=\"article:modified_time\" content=\"2025-06-04T16:42:28+00:00\" class=\"yoast-seo-meta-tag\" \/>\n<meta property=\"og:image\" content=\"https:\/\/cdn.mayaochaybo.vn\/wp-content\/uploads\/2025\/05\/ao-chay-bo-nu-form-slimfit.jpg\" class=\"yoast-seo-meta-tag\" \/>\n\t<meta property=\"og:image:width\" content=\"800\" class=\"yoast-seo-meta-tag\" \/>\n\t<meta property=\"og:image:height\" content=\"800\" class=\"yoast-seo-meta-tag\" \/>\n\t<meta property=\"og:image:type\" content=\"image\/jpeg\" class=\"yoast-seo-meta-tag\" \/>\n<meta name=\"twitter:card\" content=\"summary_large_image\" class=\"yoast-seo-meta-tag\" \/>\n<meta name=\"twitter:label1\" content=\"\u01af\u1edbc t\u00ednh th\u1eddi gian \u0111\u1ecdc\" class=\"yoast-seo-meta-tag\" \/>\n\t<meta name=\"twitter:data1\" content=\"3 ph\u00fat\" class=\"yoast-seo-meta-tag\" \/>\n<script type=\"application\/ld+json\" class=\"yoast-schema-graph\">{\"@context\":\"https:\/\/schema.org\",\"@graph\":[{\"@type\":\"WebPage\",\"@id\":\"https:\/\/mayaopickleball.vn\/ao-chay-bo-nu-mau-tim-cam-form-slimfit\/\",\"url\":\"https:\/\/mayaopickleball.vn\/ao-chay-bo-nu-mau-tim-cam-form-slimfit\/\",\"name\":\"\u00c1o ch\u1ea1y b\u1ed9 n\u1eef m\u00e0u t\u00edm cam form Slimfit - May \u00c1o Ch\u1ea1y B\u1ed9 - VN\",\"isPartOf\":{\"@id\":\"https:\/\/mayaopickleball.vn\/#website\"},\"primaryImageOfPage\":{\"@id\":\"https:\/\/mayaopickleball.vn\/ao-chay-bo-nu-mau-tim-cam-form-slimfit\/#primaryimage\"},\"image\":{\"@id\":\"https:\/\/mayaopickleball.vn\/ao-chay-bo-nu-mau-tim-cam-form-slimfit\/#primaryimage\"},\"thumbnailUrl\":\"https:\/\/cdn.mayaochaybo.vn\/wp-content\/uploads\/2025\/05\/ao-chay-bo-nu-form-slimfit.jpg\",\"datePublished\":\"2025-05-31T08:31:24+00:00\",\"dateModified\":\"2025-06-04T16:42:28+00:00\",\"description\":\"\u00c1o ch\u1ea1y b\u1ed9 n\u1eef form Slimfit n\u1ed5i b\u1eadt v\u1edbi thi\u1ebft k\u1ebf chuy\u1ec3n m\u00e0u t\u00edm \u2013 cam hi\u1ec7n \u0111\u1ea1i, ch\u1ea5t li\u1ec7u co gi\u00e3n, th\u1ea5m h\u00fat m\u1ed3 h\u00f4i v\u00e0 tho\u00e1ng kh\u00ed, mang l\u1ea1i tr\u1ea3i nghi\u1ec7m tho\u1ea3i m...\",\"breadcrumb\":{\"@id\":\"https:\/\/mayaopickleball.vn\/ao-chay-bo-nu-mau-tim-cam-form-slimfit\/#breadcrumb\"},\"inLanguage\":\"vi\",\"potentialAction\":[{\"@type\":\"ReadAction\",\"target\":[\"https:\/\/mayaopickleball.vn\/ao-chay-bo-nu-mau-tim-cam-form-slimfit\/\"]}]},{\"@type\":\"ImageObject\",\"inLanguage\":\"vi\",\"@id\":\"https:\/\/mayaopickleball.vn\/ao-chay-bo-nu-mau-tim-cam-form-slimfit\/#primaryimage\",\"url\":\"https:\/\/cdn.mayaochaybo.vn\/wp-content\/uploads\/2025\/05\/ao-chay-bo-nu-form-slimfit.jpg\",\"contentUrl\":\"https:\/\/cdn.mayaochaybo.vn\/wp-content\/uploads\/2025\/05\/ao-chay-bo-nu-form-slimfit.jpg\",\"width\":800,\"height\":800,\"caption\":\"ao-chay-bo-nu-form-slimfit\"},{\"@type\":\"BreadcrumbList\",\"@id\":\"https:\/\/mayaopickleball.vn\/ao-chay-bo-nu-mau-tim-cam-form-slimfit\/#breadcrumb\",\"itemListElement\":[{\"@type\":\"ListItem\",\"position\":1,\"name\":\"Home\",\"item\":\"https:\/\/mayaopickleball.vn\/\"},{\"@type\":\"ListItem\",\"position\":2,\"name\":\"Shop\",\"item\":\"https:\/\/mayaopickleball.vn\/shop\/\"},{\"@type\":\"ListItem\",\"position\":3,\"name\":\"\u00c1o ch\u1ea1y b\u1ed9 n\u1eef m\u00e0u t\u00edm cam form Slimfit\"}]},{\"@type\":\"WebSite\",\"@id\":\"https:\/\/mayaopickleball.vn\/#website\",\"url\":\"https:\/\/mayaopickleball.vn\/\",\"name\":\"May \u00c1o Ch\u1ea1y B\u1ed9 - VN\",\"description\":\"Chuy\u00ean May \u00c1o Ch\u1ea1y B\u1ed9 Cho \u0110\u1ed9i Nh\u00f3m, Gi\u1ea3i Ch\u1ea1y\",\"potentialAction\":[{\"@type\":\"SearchAction\",\"target\":{\"@type\":\"EntryPoint\",\"urlTemplate\":\"https:\/\/mayaopickleball.vn\/?s={search_term_string}\"},\"query-input\":{\"@type\":\"PropertyValueSpecification\",\"valueRequired\":true,\"valueName\":\"search_term_string\"}}],\"inLanguage\":\"vi\"},{\"@type\":\"LocalBusiness\",\"@id\":\"https:\/\/mayaopickleball.vn\/#localbusiness\",\"name\":\"X24 Sport - May \u00c1o Ch\u1ea1y B\u1ed9\",\"description\":\"X\u01b0\u1edfng may \u00e1o ch\u1ea1y b\u1ed9 tr\u1ef1c ti\u1ebfp, thi\u1ebft k\u1ebf ri\u00eang mi\u1ec5n ph\u00ed\",\"url\":\"https:\/\/mayaopickleball.vn\/\",\"telephone\":\"+84977130115\",\"priceRange\":\"50.000\u0111 - 500.000\u0111\",\"address\":{\"@type\":\"PostalAddress\",\"streetAddress\":\"1090\/22D Quang Trung, Ph\u01b0\u1eddng 14\",\"addressLocality\":\"G\u00f2 V\u1ea5p\",\"addressRegion\":\"TP. H\u1ed3 Ch\u00ed Minh\",\"addressCountry\":\"VN\"},\"openingHoursSpecification\":[{\"@type\":\"OpeningHoursSpecification\",\"dayOfWeek\":[\"Monday\",\"Tuesday\",\"Wednesday\",\"Thursday\",\"Friday\",\"Saturday\"],\"opens\":\"08:00\",\"closes\":\"18:00\"}]}]}<\/script>\n<!-- \/ Yoast SEO Premium plugin. -->","yoast_head_json":{"title":"\u00c1o ch\u1ea1y b\u1ed9 n\u1eef m\u00e0u t\u00edm cam form Slimfit - May \u00c1o Ch\u1ea1y B\u1ed9 - VN","description":"\u00c1o ch\u1ea1y b\u1ed9 n\u1eef form Slimfit n\u1ed5i b\u1eadt v\u1edbi thi\u1ebft k\u1ebf chuy\u1ec3n m\u00e0u t\u00edm \u2013 cam hi\u1ec7n \u0111\u1ea1i, ch\u1ea5t li\u1ec7u co gi\u00e3n, th\u1ea5m h\u00fat m\u1ed3 h\u00f4i v\u00e0 tho\u00e1ng kh\u00ed, mang l\u1ea1i tr\u1ea3i nghi\u1ec7m tho\u1ea3i m...","robots":{"index":"index","follow":"follow","max-snippet":"max-snippet:-1","max-image-preview":"max-image-preview:large","max-video-preview":"max-video-preview:-1"},"canonical":"https:\/\/mayaopickleball.vn\/ao-chay-bo-nu-mau-tim-cam-form-slimfit\/","og_locale":"vi_VN","og_type":"article","og_title":"\u00c1o ch\u1ea1y b\u1ed9 n\u1eef m\u00e0u t\u00edm cam form Slimfit","og_description":"\u00c1o ch\u1ea1y b\u1ed9 n\u1eef form Slimfit n\u1ed5i b\u1eadt v\u1edbi thi\u1ebft k\u1ebf chuy\u1ec3n m\u00e0u t\u00edm \u2013 cam hi\u1ec7n \u0111\u1ea1i, ch\u1ea5t li\u1ec7u co gi\u00e3n, th\u1ea5m h\u00fat m\u1ed3 h\u00f4i v\u00e0 tho\u00e1ng kh\u00ed, mang l\u1ea1i tr\u1ea3i nghi\u1ec7m tho\u1ea3i m...","og_url":"https:\/\/mayaopickleball.vn\/ao-chay-bo-nu-mau-tim-cam-form-slimfit\/","og_site_name":"May \u00c1o Ch\u1ea1y B\u1ed9 - VN","article_modified_time":"2025-06-04T16:42:28+00:00","og_image":[{"width":800,"height":800,"url":"https:\/\/cdn.mayaochaybo.vn\/wp-content\/uploads\/2025\/05\/ao-chay-bo-nu-form-slimfit.jpg","type":"image\/jpeg"}],"twitter_card":"summary_large_image","twitter_misc":{"\u01af\u1edbc t\u00ednh th\u1eddi gian \u0111\u1ecdc":"3 ph\u00fat"},"schema":{"@context":"https:\/\/schema.org","@graph":[{"@type":"WebPage","@id":"https:\/\/mayaopickleball.vn\/ao-chay-bo-nu-mau-tim-cam-form-slimfit\/","url":"https:\/\/mayaopickleball.vn\/ao-chay-bo-nu-mau-tim-cam-form-slimfit\/","name":"\u00c1o ch\u1ea1y b\u1ed9 n\u1eef m\u00e0u t\u00edm cam form Slimfit - May \u00c1o Ch\u1ea1y B\u1ed9 - VN","isPartOf":{"@id":"https:\/\/mayaopickleball.vn\/#website"},"primaryImageOfPage":{"@id":"https:\/\/mayaopickleball.vn\/ao-chay-bo-nu-mau-tim-cam-form-slimfit\/#primaryimage"},"image":{"@id":"https:\/\/mayaopickleball.vn\/ao-chay-bo-nu-mau-tim-cam-form-slimfit\/#primaryimage"},"thumbnailUrl":"https:\/\/cdn.mayaochaybo.vn\/wp-content\/uploads\/2025\/05\/ao-chay-bo-nu-form-slimfit.jpg","datePublished":"2025-05-31T08:31:24+00:00","dateModified":"2025-06-04T16:42:28+00:00","description":"\u00c1o ch\u1ea1y b\u1ed9 n\u1eef form Slimfit n\u1ed5i b\u1eadt v\u1edbi thi\u1ebft k\u1ebf chuy\u1ec3n m\u00e0u t\u00edm \u2013 cam hi\u1ec7n \u0111\u1ea1i, ch\u1ea5t li\u1ec7u co gi\u00e3n, th\u1ea5m h\u00fat m\u1ed3 h\u00f4i v\u00e0 tho\u00e1ng kh\u00ed, mang l\u1ea1i tr\u1ea3i nghi\u1ec7m tho\u1ea3i m...","breadcrumb":{"@id":"https:\/\/mayaopickleball.vn\/ao-chay-bo-nu-mau-tim-cam-form-slimfit\/#breadcrumb"},"inLanguage":"vi","potentialAction":[{"@type":"ReadAction","target":["https:\/\/mayaopickleball.vn\/ao-chay-bo-nu-mau-tim-cam-form-slimfit\/"]}]},{"@type":"ImageObject","inLanguage":"vi","@id":"https:\/\/mayaopickleball.vn\/ao-chay-bo-nu-mau-tim-cam-form-slimfit\/#primaryimage","url":"https:\/\/cdn.mayaochaybo.vn\/wp-content\/uploads\/2025\/05\/ao-chay-bo-nu-form-slimfit.jpg","contentUrl":"https:\/\/cdn.mayaochaybo.vn\/wp-content\/uploads\/2025\/05\/ao-chay-bo-nu-form-slimfit.jpg","width":800,"height":800,"caption":"ao-chay-bo-nu-form-slimfit"},{"@type":"BreadcrumbList","@id":"https:\/\/mayaopickleball.vn\/ao-chay-bo-nu-mau-tim-cam-form-slimfit\/#breadcrumb","itemListElement":[{"@type":"ListItem","position":1,"name":"Home","item":"https:\/\/mayaopickleball.vn\/"},{"@type":"ListItem","position":2,"name":"Shop","item":"https:\/\/mayaopickleball.vn\/shop\/"},{"@type":"ListItem","position":3,"name":"\u00c1o ch\u1ea1y b\u1ed9 n\u1eef m\u00e0u t\u00edm cam form Slimfit"}]},{"@type":"WebSite","@id":"https:\/\/mayaopickleball.vn\/#website","url":"https:\/\/mayaopickleball.vn\/","name":"May \u00c1o Ch\u1ea1y B\u1ed9 - VN","description":"Chuy\u00ean May \u00c1o Ch\u1ea1y B\u1ed9 Cho \u0110\u1ed9i Nh\u00f3m, Gi\u1ea3i Ch\u1ea1y","potentialAction":[{"@type":"SearchAction","target":{"@type":"EntryPoint","urlTemplate":"https:\/\/mayaopickleball.vn\/?s={search_term_string}"},"query-input":{"@type":"PropertyValueSpecification","valueRequired":true,"valueName":"search_term_string"}}],"inLanguage":"vi"},{"@type":"LocalBusiness","@id":"https:\/\/mayaopickleball.vn\/#localbusiness","name":"X24 Sport - May \u00c1o Ch\u1ea1y B\u1ed9","description":"X\u01b0\u1edfng may \u00e1o ch\u1ea1y b\u1ed9 tr\u1ef1c ti\u1ebfp, thi\u1ebft k\u1ebf ri\u00eang mi\u1ec5n ph\u00ed","url":"https:\/\/mayaopickleball.vn\/","telephone":"+84977130115","priceRange":"50.000\u0111 - 500.000\u0111","address":{"@type":"PostalAddress","streetAddress":"1090\/22D Quang Trung, Ph\u01b0\u1eddng 14","addressLocality":"G\u00f2 V\u1ea5p","addressRegion":"TP. H\u1ed3 Ch\u00ed Minh","addressCountry":"VN"},"openingHoursSpecification":[{"@type":"OpeningHoursSpecification","dayOfWeek":["Monday","Tuesday","Wednesday","Thursday","Friday","Saturday"],"opens":"08:00","closes":"18:00"}]}]}},"_links":{"self":[{"href":"https:\/\/mayaopickleball.vn\/wp-json\/wc\/v3\/products\/677","targetHints":{"allow":["GET","POST","PUT","PATCH","DELETE"]}}],"collection":[{"href":"https:\/\/mayaopickleball.vn\/wp-json\/wc\/v3\/products"}]}}